{
  "name": "r2k-consumer-staples",
  "description": "Russell 2000 Consumer Staples (61 companies)",
  "tickers": [
    "CALM",
    "PSMT",
    "MZTI",
    "WDFC",
    "COCO",
    "UNFI",
    "CHEF",
    "ANDE",
    "SPB",
    "HLF",
    "IPAR",
    "TPB",
    "CENTA",
    "SMPL",
    "FDP",
    "JJSF",
    "UVV",
    "DOLE",
    "IMKTA",
    "ENR",
    "EPC",
    "FIZZ",
    "WMK",
    "GO",
    "TR",
    "VITL",
    "ODC",
    "SENEA",
    "UTZ",
    "STKL",
    "JBSS",
    "AVO",
    "MAMA",
    "NATR",
    "BGS",
    "CVGW",
    "CENT",
    "NUS",
    "VLGEA",
    "NGVC",
    "BYND",
    "HNST",
    "NAGE",
    "MGPI",
    "OLPX",
    "LMNR",
    "ALCO",
    "USNA",
    "WEST",
    "SKIN",
    "MED",
    "LWAY",
    "HFFG",
    "ZVIA",
    "BRCC",
    "HAIN",
    "WALD",
    "LFVN",
    "FTLF",
    "ISPR",
    "AFRI"
  ],
  "pairs": [
    [
      "CALM",
      "PSMT"
    ],
    [
      "MZTI",
      "WDFC"
    ],
    [
      "COCO",
      "UNFI"
    ],
    [
      "CHEF",
      "ANDE"
    ],
    [
      "SPB",
      "HLF"
    ],
    [
      "IPAR",
      "TPB"
    ],
    [
      "CENTA",
      "SMPL"
    ],
    [
      "FDP",
      "JJSF"
    ],
    [
      "UVV",
      "DOLE"
    ],
    [
      "IMKTA",
      "ENR"
    ],
    [
      "EPC",
      "FIZZ"
    ],
    [
      "WMK",
      "GO"
    ],
    [
      "TR",
      "VITL"
    ],
    [
      "ODC",
      "SENEA"
    ],
    [
      "UTZ",
      "STKL"
    ],
    [
      "JBSS",
      "AVO"
    ],
    [
      "MAMA",
      "NATR"
    ],
    [
      "BGS",
      "CVGW"
    ],
    [
      "CENT",
      "NUS"
    ],
    [
      "VLGEA",
      "NGVC"
    ],
    [
      "BYND",
      "HNST"
    ],
    [
      "NAGE",
      "MGPI"
    ],
    [
      "OLPX",
      "LMNR"
    ],
    [
      "ALCO",
      "USNA"
    ],
    [
      "WEST",
      "SKIN"
    ],
    [
      "MED",
      "LWAY"
    ],
    [
      "HFFG",
      "ZVIA"
    ],
    [
      "BRCC",
      "HAIN"
    ],
    [
      "WALD",
      "LFVN"
    ],
    [
      "FTLF",
      "ISPR"
    ],
    [
      "AFRI",
      "CALM"
    ]
  ],
  "sector": "Consumer Staples",
  "vol_driver": "Russell 2000 Consumer Staples \u2014 small-cap sector fundamentals",
  "source": "iShares Russell 2000 ETF (IWM) holdings"
}